flask_statsd.py
setup.py
Flask_Statsd_Ext.egg-info/PKG-INFO
Flask_Statsd_Ext.egg-info/SOURCES.txt
Flask_Statsd_Ext.egg-info/dependency_links.txt
Flask_Statsd_Ext.egg-info/not-zip-safe
Flask_Statsd_Ext.egg-info/pbr.json
Flask_Statsd_Ext.egg-info/requires.txt
Flask_Statsd_Ext.egg-info/top_level.txt