Metadata-Version: 1.1
Name: Flask-Statsd-Ext
Version: 0.0.3
Summary: Statsd Extension for Flask
Home-page: http://nilas.com
Author: Rob McQueen
Author-email: rob@nilas.com
License: UNKNOWN
Platform: any
Classifier: Environment :: Web Environment
Classifier: Intended Audience :: Developers
Classifier: Operating System :: OS Independent
Classifier: Programming Language :: Python
Classifier: Topic :: Internet :: WWW/HTTP :: Dynamic Content
Classifier: Topic :: Software Development :: Libraries :: Python Modules
